origi/__init__.py
origi-0.0.2.dist-info/LICENSE
origi-0.0.2.dist-info/METADATA
origi-0.0.2.dist-info/WHEEL
origi-0.0.2.dist-info/top_level.txt
origi-0.0.2.dist-info/RECORD
