Metadata-Version: 2.1
Name: origi
Version: 0.0.2
Summary: 奥利给高效编程库,这里汇聚了很多高效模块
Home-page: https://github.com/pypa/sampleproject
Author: algfwq
Author-email: 3104374883@qq.com
License: UNKNOWN
Project-URL: Bug Tracker, https://github.com/pypa/sampleproject/issues
Platform: UNKNOWN
Classifier: Programming Language :: Python :: 3
Classifier: License :: OSI Approved :: MIT License
Classifier: Operating System :: OS Independent
Requires-Python: >=3.6
License-File: LICENSE
